bedspec/__init__.py
bedspec/_bedspec.py
bedspec/_reader.py
bedspec/_writer.py
bedspec/overlap/__init__.py
bedspec/overlap/_overlap.py
bedspec/py.typed
bedspec-0.7.0.dist-info/LICENSE
bedspec-0.7.0.dist-info/METADATA
bedspec-0.7.0.dist-info/WHEEL
bedspec-0.7.0.dist-info/RECORD
