Metadata-Version: 2.3
Name: bedspec
Version: 0.7.0
Summary: An HTS-specs compliant BED toolkit.
License: MIT
Keywords: bioinformatics,BED,NGS,HTS,interval
Author: Clint Valentine
Author-email: valentine.clint@gmail.com
Requires-Python: >=3.10
Classifier: Development Status :: 3 - Alpha
Classifier: Environment :: Console
Classifier: Intended Audience :: Developers
Classifier: Intended Audience :: Science/Research
Classifier: License :: OSI Approved :: MIT License
Classifier: Natural Language :: English
Classifier: Operating System :: OS Independent
Classifier: Programming Language :: Python :: 3
Classifier: Programming Language :: Python :: 3.10
Classifier: Programming Language :: Python :: 3.11
Classifier: Programming Language :: Python :: 3.12
Classifier: Programming Language :: Python :: 3.13
Classifier: Topic :: File Formats
Classifier: Topic :: Scientific/Engineering :: Bio-Informatics
Classifier: Topic :: Software Development :: Documentation
Classifier: Topic :: Software Development :: Libraries :: Python Modules
Classifier: Typing :: Typed
Requires-Dist: superintervals (>=0.2.10)
Requires-Dist: typeline (>=0.11)
Requires-Dist: typing-extensions (>=4.12)
Project-URL: Bug Tracker, https://github.com/clintval/bedspec/issues
Project-URL: Homepage, https://github.com/clintval/bedspec
Project-URL: Repository, https://github.com/clintval/bedspec
